{
  "main": {
    "id": "9e8435b4b453232b",
    "type": "split",
    "children": [
      {
        "id": "0fccfcc43052ddc1",
        "type": "tabs",
        "children": [
          {
            "id": "0f5ba167e34a5007",
            "type": "leaf",
            "state": {
              "type": "markdown",
              "state": {
                "file": "030 - Notes/Math/Derivatives.md",
                "mode": "source",
                "source": false
              },
              "icon": "lucide-file",
              "title": "Derivatives"
            }
          },
          {
            "id": "42a512fecada5927",
            "type": "leaf",
            "state": {
              "type": "markdown",
              "state": {
                "file": "030 - Notes/General ML/Expectation in ML.md",
                "mode": "source",
                "source": false
              },
              "icon": "lucide-file",
              "title": "Expectation in ML"
            }
          },
          {
            "id": "d71afa97033cd52c",
            "type": "leaf",
            "state": {
              "type": "markdown",
              "state": {
                "file": "030 - Notes/General ML/Properties of gaussians.md",
                "mode": "source",
                "source": false
              },
              "icon": "lucide-file",
              "title": "Properties of gaussians"
            }
          },
          {
            "id": "38cde6aa7f618710",
            "type": "leaf",
            "state": {
              "type": "markdown",
              "state": {
                "file": "030 - Notes/General ML/Marginal likelihood for model comparison.md",
                "mode": "source",
                "source": false
              },
              "icon": "lucide-file",
              "title": "Marginal likelihood for model comparison"
            }
          }
        ],
        "currentTab": 2
      }
    ],
    "direction": "vertical"
  },
  "left": {
    "id": "905d77f4a76c27c9",
    "type": "split",
    "children": [
      {
        "id": "f4cdcf0f0a42da44",
        "type": "tabs",
        "children": [
          {
            "id": "1b9c0ca6e568a32b",
            "type": "leaf",
            "state": {
              "type": "file-explorer",
              "state": {
                "sortOrder": "alphabetical"
              },
              "icon": "lucide-folder-closed",
              "title": "Files"
            }
          },
          {
            "id": "189f6e180bee420d",
            "type": "leaf",
            "state": {
              "type": "search",
              "state": {
                "query": "alternat",
                "matchingCase": false,
                "explainSearch": false,
                "collapseAll": false,
                "extraContext": false,
                "sortOrder": "alphabetical"
              },
              "icon": "lucide-search",
              "title": "Search"
            }
          },
          {
            "id": "3dddf0cbc2f0b3b4",
            "type": "leaf",
            "state": {
              "type": "bookmarks",
              "state": {},
              "icon": "lucide-bookmark",
              "title": "Bookmarks"
            }
          }
        ]
      }
    ],
    "direction": "horizontal",
    "width": 216.50390243530273
  },
  "right": {
    "id": "69431843e2c41654",
    "type": "split",
    "children": [
      {
        "id": "cec8b95f73d14809",
        "type": "tabs",
        "children": [
          {
            "id": "b2acdb66dbe75dcd",
            "type": "leaf",
            "state": {
              "type": "backlink",
              "state": {
                "file": "030 - Notes/General ML/Properties of gaussians.md",
                "collapseAll": false,
                "extraContext": false,
                "sortOrder": "alphabetical",
                "showSearch": false,
                "searchQuery": "",
                "backlinkCollapsed": false,
                "unlinkedCollapsed": true
              },
              "icon": "links-coming-in",
              "title": "Backlinks for Properties of gaussians"
            }
          },
          {
            "id": "b6684d682020a88c",
            "type": "leaf",
            "state": {
              "type": "outgoing-link",
              "state": {
                "file": "030 - Notes/General ML/Properties of gaussians.md",
                "linksCollapsed": false,
                "unlinkedCollapsed": true
              },
              "icon": "links-going-out",
              "title": "Outgoing links from Properties of gaussians"
            }
          },
          {
            "id": "d26860c818b47a72",
            "type": "leaf",
            "state": {
              "type": "tag",
              "state": {
                "sortOrder": "frequency",
                "useHierarchy": true
              },
              "icon": "lucide-tags",
              "title": "Tags"
            }
          },
          {
            "id": "70b3c39d89fa941d",
            "type": "leaf",
            "state": {
              "type": "outline",
              "state": {
                "file": "030 - Notes/General ML/Properties of gaussians.md"
              },
              "icon": "lucide-list",
              "title": "Outline of Properties of gaussians"
            }
          }
        ]
      }
    ],
    "direction": "horizontal",
    "width": 300,
    "collapsed": true
  },
  "left-ribbon": {
    "hiddenItems": {
      "switcher:Open quick switcher": false,
      "graph:Open graph view": false,
      "canvas:Create new canvas": false,
      "daily-notes:Open today's daily note": false,
      "templates:Insert template": false,
      "command-palette:Open command palette": false,
      "templater-obsidian:Templater": false,
      "obsidian42-brat:BRAT": false,
      "jupyter:Start Jupyter Server": false,
      "jupyter:Create Jupyter Notebook": false
    }
  },
  "active": "d71afa97033cd52c",
  "lastOpenFiles": [
    "010 - Classes/MLMI1/Resources/matrixid.pdf",
    "010 - Classes/MLMI1/Resources/examp1-solutions.pdf",
    "010 - Classes/MLMI1/Resources/01_introduction.pdf",
    "010 - Classes/MLMI1/Summary of Probabilistic Inference.md",
    "030 - Notes/General ML/Expectation in ML.md",
    "030 - Notes/General ML/Predictive distribution.md",
    "030 - Notes/Math/Probability.md",
    "010 - Classes/MLMI1/Notebook/Exercises/9.md",
    "010 - Classes/MLMI1/Notebook/Exercises/Linear regression.md",
    "030 - Notes/General ML/Properties of gaussians.md",
    "030 - Notes/Math/Derivatives.md",
    "030 - Notes/General ML/Marginal likelihood for model comparison.md",
    "030 - Notes/General ML/Alternative representation of a gaussian..md",
    "010 - Classes/MLMI1/Probabilistic modeling and Inference youtube playlist.md",
    "010 - Classes/MLMI1/Course info.md",
    "010 - Classes/MLMI1/notes.md",
    "030 - Notes/General ML/Sinus function form.md",
    "030 - Notes/Math/Integral Manipulation.md",
    "010 - Classes/MLMI1/Notebook/Exercises/Radioactive.md",
    "010 - Classes/MLMI1/Notebook/Exercises/Medical.md",
    "030 - Notes/Math/Matrixes.md",
    "010 - Classes/4F13 - Probabilistic ML/cribsheet.pdf",
    "010 - Classes/4F13 - Probabilistic ML/matrix_cookbook.pdf",
    "030 - Notes/Math/Vectors.md",
    "030 - Notes/Math/Trigonomitry.md",
    "030 - Notes/Math/Trig identities.md",
    "030 - Notes/Math/Trace.md",
    "030 - Notes/Math/Logarithms.md",
    "030 - Notes/Math/Linear transformations.md",
    "030 - Notes/Math/Integration by parts.md",
    "010 - Classes/NLP/Practical/MLMI13_Practical2023-24.pdf",
    "010 - Classes/NLP/Practical",
    "010 - Classes/NLP/Slides/lect03-tagging.pdf",
    "010 - Classes/NLP/Slides/lect04-syntax.pdf",
    "010 - Classes/NLP/Slides",
    "z - Attachments/CleanShot 2024-10-16 at 14.51.12.png",
    "z - Attachments/Pasted image 20241015104351.png",
    "z - Attachments/CleanShot 2024-10-13 at 19.58.54.png",
    "z - Attachments/CleanShot 2024-10-13 at 16.31.13.png",
    "z - Attachments/CleanShot 2024-10-11 at 17.39.38.png",
    "z - Attachments/CleanShot 2024-10-11 at 10.41.24@2x.png",
    "z - Attachments/CleanShot 2024-10-11 at 10.35.04@2x.png",
    "z - Attachments/CleanShot 2024-10-10 at 11.39.33.png",
    "z - Attachments/CleanShot 2024-09-29 at 10.04.00@2x.png",
    "z - Attachments/CleanShot 2024-09-28 at 14.45.18@2x.png"
  ]
}